jupyter_ai/_version.py
ghn_jupyter_ai-0.0.9.data/data/share/jupyter/labextensions/@jupyter-ai/core/install.json
ghn_jupyter_ai-0.0.9.dist-info/METADATA
ghn_jupyter_ai-0.0.9.dist-info/WHEEL
ghn_jupyter_ai-0.0.9.dist-info/entry_points.txt
ghn_jupyter_ai-0.0.9.dist-info/licenses/LICENSE
ghn_jupyter_ai-0.0.9.dist-info/RECORD
