Metadata-Version: 2.4
Name: ghn_jupyter_ai
Version: 0.0.9
Dynamic: Keywords
Summary: A generative AI extension for JupyterLab
Project-URL: Homepage, https://github.com/jupyterlab/jupyter-ai
Project-URL: Bug Tracker, https://github.com/jupyterlab/jupyter-ai/issues
Project-URL: Repository, https://github.com/jupyterlab/jupyter-ai.git
Author-email: Project Jupyter <jupyter@googlegroups.com>
License: BSD 3-Clause License
License-File: LICENSE
Classifier: Framework :: Jupyter
Classifier: Framework :: Jupyter :: JupyterLab
Classifier: Framework :: Jupyter :: JupyterLab :: 4
Classifier: Framework :: Jupyter :: JupyterLab :: Extensions
Classifier: Framework :: Jupyter :: JupyterLab :: Extensions :: Prebuilt
Classifier: License :: OSI Approved :: BSD License
Classifier: Programming Language :: Python
Classifier: Programming Language :: Python :: 3
Classifier: Programming Language :: Python :: 3.9
Classifier: Programming Language :: Python :: 3.10
Classifier: Programming Language :: Python :: 3.11
Classifier: Programming Language :: Python :: 3.12
Requires-Python: >=3.9
Requires-Dist: dask[distributed]
Requires-Dist: deepmerge<3,>=2.0
Requires-Dist: faiss-cpu!=1.8.0.post0,<2.0.0,>=1.8.0
Requires-Dist: ghn-jupyter-ai-magics==0.0.9
Requires-Dist: importlib-metadata>=5.2.0
Requires-Dist: jupyter-server<3,>=2.4.0
Requires-Dist: pydantic<3,>=2.10.0
Requires-Dist: traitlets>=5.6
Provides-Extra: all
Requires-Dist: arxiv; extra == 'all'
Requires-Dist: ghn-jupyter-ai-magics[all]; extra == 'all'
Requires-Dist: pypdf; extra == 'all'
Provides-Extra: dev
Requires-Dist: ghn-jupyter-ai-magics[dev]; extra == 'dev'
Provides-Extra: test
Requires-Dist: coverage; extra == 'test'
Requires-Dist: jupyter-server[test]<3,>=2.4.0; extra == 'test'
Requires-Dist: mypy; extra == 'test'
Requires-Dist: pytest; extra == 'test'
Requires-Dist: pytest-asyncio; extra == 'test'
Requires-Dist: pytest-cov; extra == 'test'
Requires-Dist: pytest-jupyter; extra == 'test'
Requires-Dist: pytest-tornasync; extra == 'test'
Requires-Dist: syrupy~=4.0.8; extra == 'test'
Requires-Dist: types-jsonschema; extra == 'test'
